jupyterlab_wall/__init__.py
jupyterlab_wall/_version.py
jupyterlab_wall/config.py
jupyterlab_wall/handlers.py
jupyterlab_wall/labextension/package.json
jupyterlab_wall/labextension/static/474.2f5467957843872e1f3b.js
jupyterlab_wall/labextension/static/474.4564a62d29422c0b81df.js
jupyterlab_wall/labextension/static/474.928f10f15cef62eede7f.js
jupyterlab_wall/labextension/static/728.fb497636c62cacf358ec.js
jupyterlab_wall/labextension/static/remoteEntry.4c357bdbaa02ea3ff875.js
jupyterlab_wall/labextension/static/remoteEntry.81cb73b393f0ee8b7457.js
jupyterlab_wall/labextension/static/remoteEntry.a5126f2dda9c1053f571.js
jupyterlab_wall/labextension/static/remoteEntry.b77cd0ec8cadbbbfcdc0.js
jupyterlab_wall/labextension/static/style.js
jupyterlab_wall/labextension/static/third-party-licenses.json
jupyterlab_wall/tests/__init__.py
jupyterlab_wall/tests/test_handlers.py
jupyterlab_wall-0.1.1.data/data/etc/jupyter/jupyter_server_config.d/jupyterlab_wall.json
jupyterlab_wall-0.1.1.data/data/share/jupyter/labextensions/jupyterlab-wall/install.json
jupyterlab_wall-0.1.1.data/data/share/jupyter/labextensions/jupyterlab-wall/package.json
jupyterlab_wall-0.1.1.data/data/share/jupyter/labextensions/jupyterlab-wall/static/474.4564a62d29422c0b81df.js
jupyterlab_wall-0.1.1.data/data/share/jupyter/labextensions/jupyterlab-wall/static/728.fb497636c62cacf358ec.js
jupyterlab_wall-0.1.1.data/data/share/jupyter/labextensions/jupyterlab-wall/static/remoteEntry.81cb73b393f0ee8b7457.js
jupyterlab_wall-0.1.1.data/data/share/jupyter/labextensions/jupyterlab-wall/static/style.js
jupyterlab_wall-0.1.1.data/data/share/jupyter/labextensions/jupyterlab-wall/static/third-party-licenses.json
jupyterlab_wall-0.1.1.dist-info/LICENSE
jupyterlab_wall-0.1.1.dist-info/METADATA
jupyterlab_wall-0.1.1.dist-info/WHEEL
jupyterlab_wall-0.1.1.dist-info/top_level.txt
jupyterlab_wall-0.1.1.dist-info/RECORD
