Metadata-Version: 2.1
Name: jupyterlab_wall
Version: 0.1.1
Summary: A JupyterLab extension to alert users of system events.
Home-page: https://github.com/mlhenderson/jupyterlab_wall
Author: Matt Henderson
License: BSD-3-Clause
Keywords: Jupyter,JupyterLab,JupyterLab3
Platform: Linux
Platform: Mac OS X
Platform: Windows
Classifier: License :: OSI Approved :: BSD License
Classifier: Programming Language :: Python
Classifier: Programming Language :: Python :: 3
Classifier: Programming Language :: Python :: 3.6
Classifier: Programming Language :: Python :: 3.7
Classifier: Programming Language :: Python :: 3.8
Classifier: Framework :: Jupyter
Requires-Python: >=3.6
License-File: LICENSE
Requires-Dist: jupyterlab ==3.*,>=3.0.0rc13
